{
  "openapi": "3.0.1",
  "info": {
    "title": "WebApiWithPostgres",
    "version": "1.0"
  },
  "paths": {
    "/api/orders": {
      "get": {
        "tags": [
          "Order"
        ],
        "responses": {
          "200": {
            "description": "OK"
          }
        }
      },
      "post": {
        "tags": [
          "Order"
        ],
        "requestBody": {
          "content": {
            "application/json": {
              "schema": {
                "$ref": "#/components/schemas/Order"
              }
            },
            "text/json": {
              "schema": {
                "$ref": "#/components/schemas/Order"
              }
            },
            "application/*+json": {
              "schema": {
                "$ref": "#/components/schemas/Order"
              }
            }
          }
        },
        "responses": {
          "200": {
            "description": "OK"
          }
        }
      }
    },
    "/api/orders/{id}": {
      "delete": {
        "tags": [
          "Order"
        ],
        "parameters": [
          {
            "name": "id",
            "in": "path",
            "required": true,
            "schema": {
              "type": "integer",
              "format": "int32"
            }
          }
        ],
        "responses": {
          "200": {
            "description": "OK"
          }
        }
      }
    },
    "/api/orders/deleteAll": {
      "delete": {
        "tags": [
          "Order"
        ],
        "responses": {
          "200": {
            "description": "OK"
          }
        }
      }
    },
    "/api/OrdersList": {
      "get": {
        "tags": [
          "OrdersList"
        ],
        "parameters": [
          {
            "name": "page",
            "in": "query",
            "schema": {
              "type": "integer",
              "format": "int32"
            }
          },
          {
            "name": "pageSize",
            "in": "query",
            "schema": {
              "type": "integer",
              "format": "int32"
            }
          },
          {
            "name": "searchText",
            "in": "query",
            "schema": {
              "type": "string"
            }
          }
        ],
        "responses": {
          "200": {
            "description": "OK"
          }
        }
      },
      "post": {
        "tags": [
          "OrdersList"
        ],
        "requestBody": {
          "content": {
            "application/json": {
              "schema": {
                "$ref": "#/components/schemas/OrderList"
              }
            },
            "text/json": {
              "schema": {
                "$ref": "#/components/schemas/OrderList"
              }
            },
            "application/*+json": {
              "schema": {
                "$ref": "#/components/schemas/OrderList"
              }
            }
          }
        },
        "responses": {
          "200": {
            "description": "OK"
          }
        }
      }
    },
    "/api/OrdersList/{id}": {
      "get": {
        "tags": [
          "OrdersList"
        ],
        "parameters": [
          {
            "name": "id",
            "in": "path",
            "required": true,
            "schema": {
              "type": "integer",
              "format": "int32"
            }
          }
        ],
        "responses": {
          "200": {
            "description": "OK"
          }
        }
      },
      "put": {
        "tags": [
          "OrdersList"
        ],
        "parameters": [
          {
            "name": "id",
            "in": "path",
            "required": true,
            "schema": {
              "type": "integer",
              "format": "int32"
            }
          }
        ],
        "requestBody": {
          "content": {
            "application/json": {
              "schema": {
                "$ref": "#/components/schemas/OrderList"
              }
            },
            "text/json": {
              "schema": {
                "$ref": "#/components/schemas/OrderList"
              }
            },
            "application/*+json": {
              "schema": {
                "$ref": "#/components/schemas/OrderList"
              }
            }
          }
        },
        "responses": {
          "200": {
            "description": "OK"
          }
        }
      },
      "delete": {
        "tags": [
          "OrdersList"
        ],
        "parameters": [
          {
            "name": "id",
            "in": "path",
            "required": true,
            "schema": {
              "type": "integer",
              "format": "int32"
            }
          }
        ],
        "responses": {
          "200": {
            "description": "OK"
          }
        }
      }
    },
    "/api/products": {
      "get": {
        "tags": [
          "Product"
        ],
        "parameters": [
          {
            "name": "page",
            "in": "query",
            "schema": {
              "type": "integer",
              "format": "int32",
              "default": 1
            }
          },
          {
            "name": "pageSize",
            "in": "query",
            "schema": {
              "type": "integer",
              "format": "int32",
              "default": 10
            }
          }
        ],
        "responses": {
          "200": {
            "description": "OK"
          }
        }
      },
      "post": {
        "tags": [
          "Product"
        ],
        "requestBody": {
          "content": {
            "application/json": {
              "schema": {
                "$ref": "#/components/schemas/Product"
              }
            },
            "text/json": {
              "schema": {
                "$ref": "#/components/schemas/Product"
              }
            },
            "application/*+json": {
              "schema": {
                "$ref": "#/components/schemas/Product"
              }
            }
          }
        },
        "responses": {
          "200": {
            "description": "OK"
          }
        }
      }
    },
    "/api/products/{id}": {
      "delete": {
        "tags": [
          "Product"
        ],
        "parameters": [
          {
            "name": "id",
            "in": "path",
            "required": true,
            "schema": {
              "type": "integer",
              "format": "int32"
            }
          }
        ],
        "responses": {
          "200": {
            "description": "OK"
          }
        }
      }
    }
  },
  "components": {
    "schemas": {
      "Order": {
        "type": "object",
        "properties": {
          "id": {
            "type": "integer",
            "format": "int32"
          },
          "items": {
            "type": "array",
            "items": {
              "$ref": "#/components/schemas/OrderItem"
            },
            "nullable": true
          },
          "totalAmount": {
            "type": "number",
            "format": "double"
          },
          "createdAt": {
            "type": "string",
            "format": "date-time"
          },
          "customerName": {
            "type": "string",
            "nullable": true
          },
          "customerAddress": {
            "type": "string",
            "nullable": true
          },
          "customerPhone": {
            "type": "string",
            "nullable": true
          }
        },
        "additionalProperties": false
      },
      "OrderItem": {
        "required": [
          "name"
        ],
        "type": "object",
        "properties": {
          "id": {
            "type": "integer",
            "format": "int32"
          },
          "name": {
            "minLength": 1,
            "type": "string"
          },
          "quantity": {
            "maximum": 2147483647,
            "minimum": 1,
            "type": "integer",
            "format": "int32"
          },
          "price": {
            "minimum": 0,01,
            "type": "number",
            "format": "double"
          },
          "orderId": {
            "type": "integer",
            "format": "int32"
          }
        },
        "additionalProperties": false
      },
      "OrderList": {
        "type": "object",
        "properties": {
          "id": {
            "type": "integer",
            "format": "int32"
          },
          "orderDate": {
            "type": "string",
            "format": "date-time"
          },
          "customerName": {
            "type": "string",
            "nullable": true
          },
          "phoneNumber": {
            "type": "string",
            "nullable": true
          },
          "productName": {
            "type": "string",
            "nullable": true
          },
          "quantity": {
            "type": "integer",
            "format": "int32"
          },
          "price": {
            "type": "number",
            "format": "double"
          },
          "total": {
            "type": "number",
            "format": "double",
            "readOnly": true
          }
        },
        "additionalProperties": false
      },
      "Product": {
        "type": "object",
        "properties": {
          "id": {
            "type": "integer",
            "format": "int32"
          },
          "name": {
            "type": "string",
            "nullable": true
          },
          "price": {
            "type": "number",
            "format": "double"
          },
          "image": {
            "type": "string",
            "nullable": true
          },
          "stock": {
            "type": "integer",
            "format": "int32"
          }
        },
        "additionalProperties": false
      }
    }
  }
}